trollfactory/__init__.py
trollfactory/cli.py
trollfactory/exceptions.py
trollfactory/functions.py
trollfactory/props/__init__.py
trollfactory/props/address.py
trollfactory/props/bank.py
trollfactory/props/birthdate.py
trollfactory/props/blood_type.py
trollfactory/props/car.py
trollfactory/props/cc.py
trollfactory/props/colors.py
trollfactory/props/document_id.py
trollfactory/props/gender.py
trollfactory/props/language.py
trollfactory/props/measurements.py
trollfactory/props/name.py
trollfactory/props/online.py
trollfactory/props/phone.py
trollfactory/props/ssn.py
trollfactory/props/langs/__init__.py
trollfactory/props/langs/english_us/__init__.py
trollfactory/props/langs/english_us/car-list.json
trollfactory/props/langs/english_us/names.json
trollfactory/props/langs/english_us/phones.json
trollfactory/props/langs/english_us/setups.json
trollfactory/props/langs/english_us/surnames.json
trollfactory/props/langs/polish/__init__.py
trollfactory/props/langs/polish/car-list.json
trollfactory/props/langs/polish/car-plate-prefixes.json
trollfactory/props/langs/polish/cities.json
trollfactory/props/langs/polish/names.json
trollfactory/props/langs/polish/phone-prefixes.json
trollfactory/props/langs/polish/phones.json
trollfactory/props/langs/polish/setups.json
trollfactory/props/langs/polish/surnames.json
TrollFactory-2.1.4.dist-info/LICENSE
TrollFactory-2.1.4.dist-info/METADATA
TrollFactory-2.1.4.dist-info/WHEEL
TrollFactory-2.1.4.dist-info/entry_points.txt
TrollFactory-2.1.4.dist-info/top_level.txt
TrollFactory-2.1.4.dist-info/RECORD
