Metadata-Version: 2.1
Name: TrollFactory
Version: 2.1.4
Summary: An amazingly accurate fake personality generator.
Home-page: UNKNOWN
Author: Stanisławowski Research & Development
Author-email: <office@stanislawowski.pl>
License: UNKNOWN
Keywords: fake,personality,personalities,generator
Platform: UNKNOWN
Classifier: Development Status :: 4 - Beta
Classifier: Environment :: Console
Classifier: Intended Audience :: Other Audience
Classifier: License :: OSI Approved :: GNU General Public License v3 (GPLv3)
Classifier: Operating System :: OS Independent
Classifier: Programming Language :: Python :: 3
Classifier: Topic :: Utilities
License-File: LICENSE
Requires-Dist: schwifty
